{"id":"11806","name":"彩绘尖桩栅栏门Painted Picket Fence Gate - black +blocksMoving +autoDefaultTrans","transitionsToward":[{"targetID":"11811","newTargetID":"11806","decay":"3s"},{"targetID":"11788","newTargetID":"11806","decay":"2s"},{"targetID":"31128","newTargetID":"11806","decay":"1s"},{"targetID":"11788","newTargetID":"11806","hand":true,"tool":true},{"actorID":"1541","targetID":"11785","newTargetID":"11806","hand":true}],"transitionsAway":[{"targetID":"11806","newTargetID":"11788","hand":true,"tool":true},{"actorID":"441","newActorUses":"-1","newActorWeight":0.02,"targetID":"11806","newActorID":"441","newTargetID":"11811","hand":true,"tool":true},{"actorID":"441","actorUses":"last","targetID":"11806","newActorID":"858","newTargetID":"11811","hand":true},{"actorID":"455","newActorUses":"-1","newActorWeight":0.04,"targetID":"11806","newActorID":"455","newTargetID":"11768","hand":true,"tool":true},{"actorID":"455","actorUses":"last","targetID":"11806","newActorID":"862","newTargetID":"11768","hand":true}],"transitionsTimed":[],"craftable":false,"sounds":[78],"techTree":[{"decay":"3s"},{"id":"11811","nodes":[{"id":"441","nodes":[{"id":"443","nodes":[]},{"id":"69","nodes":[]}]},{"id":"11806","nodes":[{"decay":"3s"},{"id":"11811","nodes":[]}]}]}]}