{"id":"25004","name":"菌丝湿蘑菇地Wet Mushroom Field with Hyphae\r","transitionsToward":[{"actorID":"382","targetID":"25003","newActorID":"235","newTargetID":"25004","hand":true}],"transitionsAway":[],"transitionsTimed":[{"targetID":"25004","newTargetID":"25005","decay":"15m"}],"craftable":true,"depth":97,"clothing":"n\r","insulation":0,"sounds":[297],"techTree":[{"id":"382","nodes":[{"id":"235","nodes":[{"id":"283","nodes":[]}]},{"id":"141","nodes":null}]},{"id":"25003","nodes":[{"decay":"2m"},{"id":"25009","nodes":[{"id":"382","nodes":[]},{"id":"25002","nodes":[]}]}]}],"recipe":{"steps":[[{"id":"67","count":2,"uses":"x2","mainBranch":true,"depth":8,"actorID":"34","targetID":"64","hand":true}],[{"id":"557","mainBranch":true,"depth":7,"actorID":"67","targetID":"67","hand":true},{"id":"5235","depth":7,"subSteps":[[{"id":"213","depth":8,"actorID":"139","targetID":"1101","targetUses":"max","hand":true}],[{"id":"5235","depth":7,"actorID":"7058","targetID":"213","hand":true}]]}],[{"id":"25000","mainBranch":true,"depth":6,"actorID":"557","targetID":"5235","hand":true},{"id":"227","depth":6,"subSteps":[[{"id":"224","depth":9,"actorID":"34","targetID":"242","hand":true}],[{"id":"225","depth":8,"targetID":"224","hand":true}],[{"id":"226","depth":7,"actorID":"64","targetID":"225","hand":true}],[{"id":"227","depth":6,"targetID":"226","hand":true}]]}],[{"id":"25001","mainBranch":true,"depth":5,"actorID":"227","targetID":"25000","hand":true},{"id":"1137","depth":5,"actorID":"235","targetID":"1101","targetUses":"max","hand":true}],[{"id":"25007","mainBranch":true,"depth":4,"actorID":"1137","targetID":"25001","hand":true},{"id":"837","depth":4,"targetID":"838","hand":true}],[{"id":"25002","mainBranch":true,"depth":3,"actorID":"837","targetID":"25007","hand":true},{"id":"382","count":2,"uses":"x2","depth":3,"actorID":"235","targetID":"141","hand":true}],[{"id":"25009","mainBranch":true,"depth":2,"actorID":"382","targetID":"25002","hand":true}],[{"id":"25003","mainBranch":true,"depth":1,"targetID":"25009","decay":"2m"}],[{"id":"25004","mainBranch":true,"depth":0,"actorID":"382","targetID":"25003","hand":true}]],"ingredients":["7058","235","838","1101","139","34","64","141","242"]}}