{"id":"25333","name":"3D象棋投影仪3D Chess Projector  -  +tapoutTrigger,-2,-2 red reset","transitionsToward":[{"targetID":"25332","newTargetID":"25333","decay":"1s"}],"transitionsAway":[{"actorID":"25333","targetID":"25353","newTargetID":"25283","hand":true}],"transitionsTimed":[{"targetID":"25333","newTargetID":"25334","decay":"1s"}],"craftable":false,"blocksWalking":true,"techTree":[{"decay":"1s"},{"id":"25332","nodes":[{"decay":"1s"},{"id":"25331","nodes":[{"decay":"1s"},{"id":"25330","nodes":[]}]}]}]}