{"id":"25359","name":"3D象棋投影仪3D Chess Projector  -  +tapoutTrigger,1,1,0,4 red reset\r","transitionsToward":[{"targetID":"25346","newTargetID":"25359","decay":"1s"}],"transitionsAway":[{"actorID":"25359","targetID":"25353","newTargetID":"25356","hand":true},{"actorID":"25359","targetID":"25397","newTargetID":"25356","hand":true},{"actorID":"25359","targetID":"25400","newTargetID":"25356","hand":true},{"actorID":"25359","targetID":"25401","newTargetID":"25356","hand":true}],"transitionsTimed":[{"targetID":"25359","newTargetID":"25358","decay":"1s"}],"craftable":false,"clothing":"n\r","insulation":0,"blocksWalking":true,"techTree":[{"decay":"1s"},{"id":"25346","nodes":[{"decay":"1s"},{"id":"25345","nodes":[{"decay":"1s"},{"id":"25344","nodes":[]}]}]}]}