{"id":"26026","name":"转子 Rotor without Shaft","transitionsToward":[{"actorID":"2531","targetID":"26025","newTargetID":"26026","hand":true}],"transitionsAway":[{"targetID":"26026","newActorID":"2296","newTargetID":"26027","hand":true},{"actorID":"2296","targetID":"26026","newTargetID":"26027","hand":true}],"transitionsTimed":[],"craftable":false,"size":3,"minPickupAge":3,"techTree":[{"id":"2531","nodes":[{"id":"2530","nodes":[{"id":"12490","nodes":[]}]},{"id":"2503","nodes":[{"id":"459","nodes":[]},{"id":"2498","nodes":[]}]}]},{"id":"26025","nodes":[{"id":"2531","nodes":[{"id":"2530","nodes":[]},{"id":"2503","nodes":[]}]},{"id":"26024","nodes":[{"id":"26025","nodes":[]}]}]}]}