{"id":"27943","name":"湿润的郁金香苗 Wet Tulip Spout -  Red","transitionsToward":[{"actorID":"235","targetID":"27942","newActorID":"382","newTargetID":"27943","hand":true},{"actorID":"209","targetID":"27942","newActorID":"210","newTargetID":"27943","hand":true},{"actorID":"7029","targetID":"27942","newActorID":"7013","newTargetID":"27943","hand":true},{"actorID":"7013","newActorUses":"-1","targetID":"27942","newActorID":"7013","newTargetID":"27943","hand":true,"tool":true},{"actorID":"7013","actorUses":"last","targetID":"27942","newActorID":"7014","newTargetID":"27943","hand":true}],"transitionsAway":[],"transitionsTimed":[{"targetID":"27943","newTargetID":"27944","decay":"20m"}],"craftable":false,"size":3,"minPickupAge":14,"speedMult":0.75,"sounds":[297],"techTree":[{"id":"235","nodes":[{"id":"283","nodes":[{"id":"284","nodes":[]},{"id":"282","nodes":[]}]}]},{"id":"27942","nodes":[{"decay":"10m"},{"id":"27941","nodes":[{"id":"235","nodes":[]},{"id":"27940","nodes":[]}]}]}]}