{"id":"28737","name":"一碗面团和水 Bowl of Dough and Water\r","transitionsToward":[{"actorID":"382","targetID":"252","targetUses":"max","newActorID":"235","newTargetID":"28737","hand":true}],"transitionsAway":[{"actorID":"852","targetID":"28737","newActorID":"852","newTargetID":"28738","hand":true,"tool":true}],"transitionsTimed":[],"craftable":true,"depth":18,"clothing":"n\r","insulation":0,"size":2,"minPickupAge":3,"sounds":[349],"techTree":[{"id":"382","nodes":[{"id":"235","nodes":[{"id":"283","nodes":[]}]},{"id":"141","nodes":null}]},{"id":"252","nodes":[{"id":"382","nodes":[{"id":"235","nodes":[]},{"id":"141","nodes":null}]},{"id":"251","nodes":[{"id":"33","nodes":null},{"id":"245","nodes":[]}]}]}],"recipe":{"steps":[[{"id":"224","mainBranch":true,"depth":6,"actorID":"34","targetID":"242","hand":true}],[{"id":"225","mainBranch":true,"depth":5,"targetID":"224","hand":true}],[{"id":"226","mainBranch":true,"depth":4,"actorID":"64","targetID":"225","hand":true}],[{"id":"245","mainBranch":true,"depth":3,"actorID":"235","targetID":"226","hand":true}],[{"id":"251","mainBranch":true,"depth":2,"actorID":"33","targetID":"245","hand":true},{"id":"382","count":2,"uses":"x2","depth":2,"actorID":"235","targetID":"141","hand":true}],[{"id":"252","uses":"max","mainBranch":true,"depth":1,"actorID":"382","targetID":"251","hand":true}],[{"id":"28737","mainBranch":true,"depth":0,"actorID":"382","targetID":"252","targetUses":"max","hand":true}]],"ingredients":["235","34","64","141","33","242"]}}