{"id":"30947","name":"中国长碟上的熟猪Cooked Pig on China Long Plate","transitionsToward":[{"actorID":"30648","targetID":"8502","newActorID":"30947","newTargetID":"8510","hand":true},{"actorID":"8503","targetID":"30648","newActorID":"291","newTargetID":"30947","hand":true}],"transitionsAway":[{"actorID":"30947","targetID":"291","newActorID":"30648","newTargetID":"8503","hand":true},{"actorID":"30947","targetID":"6701","newActorID":"30947","newTargetID":"11104","hand":true,"tool":true},{"actorID":"11104","targetID":"30947","newActorID":"11106","newTargetID":"30947","targetRemains":true,"hand":true},{"actorID":"8511","actorUses":"max","targetID":"30947","newActorID":"292","newTargetID":"30948","hand":true}],"transitionsTimed":[],"craftable":false,"minPickupAge":3,"techTree":[{"id":"30648","nodes":[{"id":"30649","nodes":[{"id":"30648","nodes":[]},{"id":"30648","nodes":[]}]}]},{"id":"8502","nodes":[{"decay":"1m"},{"id":"8501","nodes":[{"decay":"2m"},{"id":"8499","nodes":[]}]}]}]}